ptulsconv/__init__.py
ptulsconv/__main__.py
ptulsconv/broadcast_timecode.py
ptulsconv/commands.py
ptulsconv/docparser/__init__.py
ptulsconv/docparser/adr_entity.py
ptulsconv/docparser/doc_entity.py
ptulsconv/docparser/generic_entity.py
ptulsconv/docparser/pt_doc_parser.py
ptulsconv/docparser/tag_compiler.py
ptulsconv/docparser/tag_mapping.py
ptulsconv/docparser/tagged_string_parser_visitor.py
ptulsconv/footage.py
ptulsconv/movie_export.py
ptulsconv/pdf/__init__.py
ptulsconv/pdf/continuity.py
ptulsconv/pdf/line_count.py
ptulsconv/pdf/recordist_log.py
ptulsconv/pdf/summary_log.py
ptulsconv/pdf/supervisor_1pg.py
ptulsconv/pdf/talent_sides.py
ptulsconv/reporting.py
ptulsconv/validations.py
ptulsconv/xml/common.py
ptulsconv/xslt/AvidMarkers.xsl
ptulsconv/xslt/SRT.xsl
ptulsconv-4.0.0.dist-info/WHEEL
ptulsconv-4.0.0.dist-info/entry_points.txt
ptulsconv-4.0.0.dist-info/METADATA
ptulsconv-4.0.0.dist-info/RECORD
