Metadata-Version: 2.3
Name: ptulsconv
Version: 4.0.0
Summary: Read Pro Tools Text exports and generate PDF ADR Reports, JSON
Keywords: text-processing,parsers,film,broadcast,editing,editorial
Author: Jamie Hardt
Author-email: Jamie Hardt <<jamiehardt@me.com>>
License: MIT License
Classifier: License :: OSI Approved :: MIT License
Classifier: Topic :: Multimedia
Classifier: Topic :: Multimedia :: Sound/Audio
Classifier: Programming Language :: Python :: 3.9
Classifier: Programming Language :: Python :: 3.10
Classifier: Programming Language :: Python :: 3.11
Classifier: Programming Language :: Python :: 3.12
Classifier: Programming Language :: Python :: 3.13
Classifier: Development Status :: 5 - Production/Stable
Classifier: Topic :: Text Processing :: Filters
Requires-Dist: parsimonious>=0.10.0
Requires-Dist: py-ptsl>=600.0.0
Requires-Dist: reportlab>=4.4.4
Requires-Dist: tqdm>=4.67.1
Requires-Dist: sphinx>=7.4.7 ; extra == 'doc'
Requires-Dist: sphinx-rtd-theme>=3.0.2 ; extra == 'doc'
Requires-Python: >=3.9
Project-URL: Documentation, https://ptulsconv.readthedocs.io/
Project-URL: Issues, https://github.com/iluvcapra/ptulsconv/issues
Project-URL: Source, https://github.com/iluvcapra/ptulsconv
Provides-Extra: doc
